fmu/__init__.py
fmu/datamodels/__init__.py
fmu/datamodels/_schema_base.py
fmu/datamodels/_schema_urls.py
fmu/datamodels/py.typed
fmu/datamodels/types.py
fmu/datamodels/version.py
fmu/datamodels/common/__init__.py
fmu/datamodels/common/access.py
fmu/datamodels/common/enums.py
fmu/datamodels/common/masterdata.py
fmu/datamodels/common/tracklog.py
fmu/datamodels/context/__init__.py
fmu/datamodels/context/mappings.py
fmu/datamodels/fmu_results/__init__.py
fmu/datamodels/fmu_results/data.py
fmu/datamodels/fmu_results/enums.py
fmu/datamodels/fmu_results/fields.py
fmu/datamodels/fmu_results/fmu_results.py
fmu/datamodels/fmu_results/global_configuration.py
fmu/datamodels/fmu_results/specification.py
fmu/datamodels/fmu_results/standard_result.py
fmu/datamodels/parameters/__init__.py
fmu/datamodels/parameters/metadata.py
fmu/datamodels/parameters/table_schema.py
fmu/datamodels/standard_results/__init__.py
fmu/datamodels/standard_results/enums.py
fmu/datamodels/standard_results/field_outline.py
fmu/datamodels/standard_results/fluid_contact_outline.py
fmu/datamodels/standard_results/inplace_volumes.py
fmu/datamodels/standard_results/structure_depth_fault_lines.py
fmu_datamodels-0.17.3.dist-info/licenses/LICENSE
fmu_datamodels-0.17.3.dist-info/METADATA
fmu_datamodels-0.17.3.dist-info/WHEEL
fmu_datamodels-0.17.3.dist-info/top_level.txt
fmu_datamodels-0.17.3.dist-info/RECORD
