Metadata-Version: 2.4
Name: fmu-datamodels
Version: 0.17.3
Summary: FMU data standard, including models and schemas
Author-email: Equinor <fg-fmu_atlas@equinor.com>
License: Apache 2.0
Project-URL: Homepage, https://github.com/equinor/fmu-datamodels
Project-URL: Repository, https://github.com/equinor/fmu-datamodels
Project-URL: Issues, https://github.com/equinor/fmu-datamodels/issues
Project-URL: Documentation, https://fmu-dataio.readthedocs.io
Keywords: fmu,sumo
Classifier: Development Status :: 5 - Production/Stable
Classifier: Intended Audience :: Developers
Classifier: Intended Audience :: Science/Research
Classifier: License :: OSI Approved :: Apache Software License
Classifier: Natural Language :: English
Classifier: Programming Language :: Python
Classifier: Programming Language :: Python :: 3.11
Classifier: Programming Language :: Python :: 3.12
Classifier: Programming Language :: Python :: 3.13
Classifier: Topic :: Scientific/Engineering
Classifier: Topic :: Scientific/Engineering :: Physics
Classifier: Topic :: Software Development :: Libraries
Classifier: Topic :: Utilities
Requires-Python: >=3.11
License-File: LICENSE
Requires-Dist: pydantic
Provides-Extra: dev
Requires-Dist: coverage>=4.1; extra == "dev"
Requires-Dist: hypothesis; extra == "dev"
Requires-Dist: mypy; extra == "dev"
Requires-Dist: pyarrow; extra == "dev"
Requires-Dist: pyarrow-stubs; extra == "dev"
Requires-Dist: pytest; extra == "dev"
Requires-Dist: pytest-cov; extra == "dev"
Requires-Dist: pytest-mock; extra == "dev"
Requires-Dist: pytest-runner; extra == "dev"
Requires-Dist: pytest-xdist; extra == "dev"
Requires-Dist: ruff; extra == "dev"
Requires-Dist: xtgeo>=2.16; extra == "dev"
Provides-Extra: docs
Requires-Dist: pydocstyle; extra == "docs"
Dynamic: license-file
